pulp_npm/__init__.py
pulp_npm/pytest_plugin.py
pulp_npm/app/__init__.py
pulp_npm/app/models.py
pulp_npm/app/serializers.py
pulp_npm/app/settings.py
pulp_npm/app/urls.py
pulp_npm/app/utils.py
pulp_npm/app/viewsets.py
pulp_npm/app/migrations/0001_initial.py
pulp_npm/app/migrations/0001_squashed_0003_alter_npmdistribution_distribution_ptr_and_more.py
pulp_npm/app/migrations/0002_swap_distribution_model.py
pulp_npm/app/migrations/0003_alter_npmdistribution_distribution_ptr_and_more.py
pulp_npm/app/migrations/0004_alter_package_unique_together_package__pulp_domain_and_more.py
pulp_npm/app/migrations/__init__.py
pulp_npm/app/tasks/__init__.py
pulp_npm/app/tasks/synchronizing.py
pulp_npm/app/webserver_snippets/__init__.py
pulp_npm/app/webserver_snippets/apache.conf
pulp_npm/app/webserver_snippets/nginx.conf
pulp_npm/tests/__init__.py
pulp_npm/tests/functional/__init__.py
pulp_npm/tests/functional/constants.py
pulp_npm/tests/functional/utils.py
pulp_npm/tests/functional/api/__init__.py
pulp_npm/tests/functional/api/test_crud_content_unit.py
pulp_npm/tests/functional/api/test_crud_remotes.py
pulp_npm/tests/functional/api/test_download_content.py
pulp_npm/tests/functional/api/test_download_policies.py
pulp_npm/tests/functional/api/test_pull_through_caching.py
pulp_npm/tests/functional/api/test_sync.py
pulp_npm/tests/performance/__init__.py
pulp_npm/tests/unit/__init__.py
pulp_npm/tests/unit/test_serializers.py
pulp_npm-0.5.0.dist-info/licenses/LICENSE
pulp_npm-0.5.0.dist-info/METADATA
pulp_npm-0.5.0.dist-info/WHEEL
pulp_npm-0.5.0.dist-info/entry_points.txt
pulp_npm-0.5.0.dist-info/top_level.txt
pulp_npm-0.5.0.dist-info/RECORD
