Metadata-Version: 2.4
Name: pulp-npm
Version: 0.5.0
Summary: pulp-npm plugin for the Pulp Project
Author-email: Pulp Team <pulp-list@redhat.com>
Project-URL: Homepage, https://pulpproject.org
Project-URL: Documentation, https://pulpproject.org/pulp_npm/
Project-URL: Repository, https://github.com/pulp/pulp_npm
Project-URL: Bug Tracker, https://github.com/pulp/pulp_npm/issues
Project-URL: Changelog, https://pulpproject.org/pulp_npm/changes/
Classifier: License :: OSI Approved :: GNU General Public License v2 or later (GPLv2+)
Classifier: Operating System :: POSIX :: Linux
Classifier: Framework :: Django
Classifier: Programming Language :: Python
Classifier: Programming Language :: Python :: 3
Classifier: Programming Language :: Python :: 3.10
Classifier: Programming Language :: Python :: 3.11
Classifier: Programming Language :: Python :: 3.12
Requires-Python: >=3.11
License-File: LICENSE
Requires-Dist: pulpcore<3.115,>=3.85.0
Dynamic: license-file
